bilalhaiderid/__init__.py
bilalhaiderid-0.0.1.dist-info/LICENSE
bilalhaiderid-0.0.1.dist-info/METADATA
bilalhaiderid-0.0.1.dist-info/WHEEL
bilalhaiderid-0.0.1.dist-info/top_level.txt
bilalhaiderid-0.0.1.dist-info/RECORD
