Metadata-Version: 2.1
Name: bilalhaiderid
Version: 0.0.1
Summary: bilalhaiderid
Author: BilalHaiderID
Author-email: bilalhaiderid@gmail.com
Keywords: testing,bilalhaiderid
Classifier: Development Status :: 1 - Planning
Classifier: Intended Audience :: Developers
Classifier: Programming Language :: Python :: 3
Classifier: Operating System :: Unix
Classifier: Operating System :: MacOS :: MacOS X
Classifier: Operating System :: Microsoft :: Windows
License-File: LICENSE
